eat_money/CalorieNinja.py
eat_money/__init__.py
eat_money/__main__.py
eat_money/comic.ttf
eat_money/data.db
eat_money/eatmoneylogo.png
eat_money/food.py
eat_money/main.py
eat_money/preferences.json
eat_money/text_helper.py
eat_money-0.9.9.dist-info/LICENSE.txt
eat_money-0.9.9.dist-info/METADATA
eat_money-0.9.9.dist-info/WHEEL
eat_money-0.9.9.dist-info/entry_points.txt
eat_money-0.9.9.dist-info/top_level.txt
eat_money-0.9.9.dist-info/RECORD
