Metadata-Version: 2.1
Name: eat-money
Version: 0.9.9
Summary: Calorie/Spending tracker
License: MIT License        
License-File: LICENSE.txt
Requires-Dist: requests
Requires-Dist: Kivy
Requires-Dist: KivyMD
